{
  "generated_at": "2026-05-15T11:33:31.247Z",
  "config": {
    "period_days": 90,
    "from_date": "2026-02-14",
    "volatility_score_threshold": 60,
    "top_n_patterns": 10
  },
  "notes": [
    "in_kuzure_probability カラムは DB に存在しないため volatility_score>=60 を代理指標として使用。",
    "outcome_distribution は現スナップショットのみ保持 → 現分布を全期間に適用する近似値。",
    "対象レース: volatility_level=high & score>=60 / top_pick!=1 / rank1=top_pick の3条件すべてを満たすもの。",
    "買い目: outcome_distribution の first_boat=top_pick パターン Top10 を3連単10点×100円。"
  ],
  "filter_breakdown": {
    "high_races_with_result": 1490,
    "top_pick_not_1": 2999,
    "top_pick_won": 622,
    "with_distribution_data": 622
  },
  "overall": {
    "total_races": 622,
    "hit_count": 508,
    "hit_rate": 0.8167,
    "recovery_rate": 1.0169,
    "dist_investment": 620000,
    "dist_payout": 630500,
    "ai_hit_count": 51,
    "ai_hit_rate": 0.082,
    "ai_recovery_rate": 0.5195,
    "lift_vs_ai_only": 0.4975
  },
  "by_volatility_level": [
    {
      "band": "high(score 60-69)",
      "total_races": 164,
      "hit_count": 132,
      "hit_rate": 0.8049,
      "recovery_rate": 0.8581,
      "dist_investment": 163300,
      "dist_payout": 140130,
      "ai_hit_count": 7,
      "ai_hit_rate": 0.0427,
      "ai_recovery_rate": 0.1598,
      "lift_vs_ai_only": 0.6984
    },
    {
      "band": "high(score 70-84)",
      "total_races": 361,
      "hit_count": 309,
      "hit_rate": 0.856,
      "recovery_rate": 1.1454,
      "dist_investment": 359700,
      "dist_payout": 412010,
      "ai_hit_count": 37,
      "ai_hit_rate": 0.1025,
      "ai_recovery_rate": 0.5102,
      "lift_vs_ai_only": 0.6352
    },
    {
      "band": "high(score 85+)",
      "total_races": 97,
      "hit_count": 67,
      "hit_rate": 0.6907,
      "recovery_rate": 0.8078,
      "dist_investment": 97000,
      "dist_payout": 78360,
      "ai_hit_count": 7,
      "ai_hit_rate": 0.0722,
      "ai_recovery_rate": 1.1619,
      "lift_vs_ai_only": -0.354
    }
  ],
  "by_model": [
    {
      "model_id": "upsetFocus",
      "total_races": 224,
      "hit_count": 187,
      "hit_rate": 0.8348,
      "recovery_rate": 1.1227,
      "dist_investment": 223300,
      "dist_payout": 250690,
      "ai_hit_count": 15,
      "ai_hit_rate": 0.067,
      "ai_recovery_rate": 0.825,
      "lift_vs_ai_only": 0.2977
    },
    {
      "model_id": "safeBet",
      "total_races": 223,
      "hit_count": 182,
      "hit_rate": 0.8161,
      "recovery_rate": 1.0482,
      "dist_investment": 222200,
      "dist_payout": 232900,
      "ai_hit_count": 11,
      "ai_hit_rate": 0.0493,
      "ai_recovery_rate": 0.2,
      "lift_vs_ai_only": 0.8482
    },
    {
      "model_id": "standard",
      "total_races": 175,
      "hit_count": 139,
      "hit_rate": 0.7943,
      "recovery_rate": 0.8419,
      "dist_investment": 174500,
      "dist_payout": 146910,
      "ai_hit_count": 25,
      "ai_hit_rate": 0.1429,
      "ai_recovery_rate": 0.5354,
      "lift_vs_ai_only": 0.3065
    }
  ],
  "by_venue": [
    {
      "venue_code": 8,
      "venue_name": "常滑",
      "total_races": 29,
      "hit_count": 27,
      "hit_rate": 0.931,
      "recovery_rate": 2.3803,
      "dist_investment": 29000,
      "dist_payout": 69030,
      "ai_hit_count": 2,
      "ai_hit_rate": 0.069,
      "ai_recovery_rate": 0.3966,
      "lift_vs_ai_only": 1.9838
    },
    {
      "venue_code": 23,
      "venue_name": "唐津",
      "total_races": 14,
      "hit_count": 14,
      "hit_rate": 1,
      "recovery_rate": 2.2511,
      "dist_investment": 13500,
      "dist_payout": 30390,
      "ai_hit_count": 0,
      "ai_hit_rate": 0,
      "ai_recovery_rate": 0,
      "lift_vs_ai_only": 2.2511
    },
    {
      "venue_code": 19,
      "venue_name": "下関",
      "total_races": 24,
      "hit_count": 23,
      "hit_rate": 0.9583,
      "recovery_rate": 1.5325,
      "dist_investment": 24000,
      "dist_payout": 36780,
      "ai_hit_count": 3,
      "ai_hit_rate": 0.125,
      "ai_recovery_rate": 3.7833,
      "lift_vs_ai_only": -2.2508
    },
    {
      "venue_code": 13,
      "venue_name": "尼崎",
      "total_races": 36,
      "hit_count": 31,
      "hit_rate": 0.8611,
      "recovery_rate": 1.4572,
      "dist_investment": 36000,
      "dist_payout": 52460,
      "ai_hit_count": 1,
      "ai_hit_rate": 0.0278,
      "ai_recovery_rate": 0.225,
      "lift_vs_ai_only": 1.2322
    },
    {
      "venue_code": 15,
      "venue_name": "丸亀",
      "total_races": 13,
      "hit_count": 13,
      "hit_rate": 1,
      "recovery_rate": 1.28,
      "dist_investment": 13000,
      "dist_payout": 16640,
      "ai_hit_count": 1,
      "ai_hit_rate": 0.0769,
      "ai_recovery_rate": 0.2462,
      "lift_vs_ai_only": 1.0338
    },
    {
      "venue_code": 3,
      "venue_name": "江戸川",
      "total_races": 33,
      "hit_count": 31,
      "hit_rate": 0.9394,
      "recovery_rate": 1.2648,
      "dist_investment": 33000,
      "dist_payout": 41740,
      "ai_hit_count": 3,
      "ai_hit_rate": 0.0909,
      "ai_recovery_rate": 0.3909,
      "lift_vs_ai_only": 0.8739
    },
    {
      "venue_code": 6,
      "venue_name": "浜名湖",
      "total_races": 48,
      "hit_count": 41,
      "hit_rate": 0.8542,
      "recovery_rate": 1.1919,
      "dist_investment": 48000,
      "dist_payout": 57210,
      "ai_hit_count": 5,
      "ai_hit_rate": 0.1042,
      "ai_recovery_rate": 0.6979,
      "lift_vs_ai_only": 0.494
    },
    {
      "venue_code": 20,
      "venue_name": "若松",
      "total_races": 5,
      "hit_count": 5,
      "hit_rate": 1,
      "recovery_rate": 1.108,
      "dist_investment": 5000,
      "dist_payout": 5540,
      "ai_hit_count": 1,
      "ai_hit_rate": 0.2,
      "ai_recovery_rate": 0.58,
      "lift_vs_ai_only": 0.528
    },
    {
      "venue_code": 21,
      "venue_name": "芦屋",
      "total_races": 19,
      "hit_count": 16,
      "hit_rate": 0.8421,
      "recovery_rate": 1.0421,
      "dist_investment": 19000,
      "dist_payout": 19800,
      "ai_hit_count": 2,
      "ai_hit_rate": 0.1053,
      "ai_recovery_rate": 1.1632,
      "lift_vs_ai_only": -0.1211
    },
    {
      "venue_code": 5,
      "venue_name": "多摩川",
      "total_races": 27,
      "hit_count": 26,
      "hit_rate": 0.963,
      "recovery_rate": 1.0163,
      "dist_investment": 25800,
      "dist_payout": 26220,
      "ai_hit_count": 2,
      "ai_hit_rate": 0.0741,
      "ai_recovery_rate": 0.3296,
      "lift_vs_ai_only": 0.6866
    },
    {
      "venue_code": 12,
      "venue_name": "住之江",
      "total_races": 30,
      "hit_count": 24,
      "hit_rate": 0.8,
      "recovery_rate": 0.9949,
      "dist_investment": 29700,
      "dist_payout": 29550,
      "ai_hit_count": 2,
      "ai_hit_rate": 0.0667,
      "ai_recovery_rate": 0.19,
      "lift_vs_ai_only": 0.8049
    },
    {
      "venue_code": 10,
      "venue_name": "三国",
      "total_races": 25,
      "hit_count": 23,
      "hit_rate": 0.92,
      "recovery_rate": 0.9544,
      "dist_investment": 25000,
      "dist_payout": 23860,
      "ai_hit_count": 5,
      "ai_hit_rate": 0.2,
      "ai_recovery_rate": 0.828,
      "lift_vs_ai_only": 0.1264
    },
    {
      "venue_code": 17,
      "venue_name": "宮島",
      "total_races": 19,
      "hit_count": 16,
      "hit_rate": 0.8421,
      "recovery_rate": 0.9421,
      "dist_investment": 19000,
      "dist_payout": 17900,
      "ai_hit_count": 0,
      "ai_hit_rate": 0,
      "ai_recovery_rate": 0,
      "lift_vs_ai_only": 0.9421
    },
    {
      "venue_code": 11,
      "venue_name": "びわこ",
      "total_races": 40,
      "hit_count": 29,
      "hit_rate": 0.725,
      "recovery_rate": 0.9278,
      "dist_investment": 40000,
      "dist_payout": 37110,
      "ai_hit_count": 3,
      "ai_hit_rate": 0.075,
      "ai_recovery_rate": 0.4925,
      "lift_vs_ai_only": 0.4353
    },
    {
      "venue_code": 2,
      "venue_name": "戸田",
      "total_races": 50,
      "hit_count": 42,
      "hit_rate": 0.84,
      "recovery_rate": 0.925,
      "dist_investment": 50000,
      "dist_payout": 46250,
      "ai_hit_count": 3,
      "ai_hit_rate": 0.06,
      "ai_recovery_rate": 0.21,
      "lift_vs_ai_only": 0.715
    },
    {
      "venue_code": 7,
      "venue_name": "蒲郡",
      "total_races": 50,
      "hit_count": 38,
      "hit_rate": 0.76,
      "recovery_rate": 0.7562,
      "dist_investment": 50000,
      "dist_payout": 37810,
      "ai_hit_count": 4,
      "ai_hit_rate": 0.08,
      "ai_recovery_rate": 0.252,
      "lift_vs_ai_only": 0.5042
    },
    {
      "venue_code": 16,
      "venue_name": "児島",
      "total_races": 13,
      "hit_count": 12,
      "hit_rate": 0.9231,
      "recovery_rate": 0.6285,
      "dist_investment": 13000,
      "dist_payout": 8170,
      "ai_hit_count": 2,
      "ai_hit_rate": 0.1538,
      "ai_recovery_rate": 0.7923,
      "lift_vs_ai_only": -0.1638
    },
    {
      "venue_code": 4,
      "venue_name": "平和島",
      "total_races": 51,
      "hit_count": 30,
      "hit_rate": 0.5882,
      "recovery_rate": 0.5776,
      "dist_investment": 51000,
      "dist_payout": 29460,
      "ai_hit_count": 4,
      "ai_hit_rate": 0.0784,
      "ai_recovery_rate": 0.2333,
      "lift_vs_ai_only": 0.3443
    },
    {
      "venue_code": 22,
      "venue_name": "福岡",
      "total_races": 17,
      "hit_count": 9,
      "hit_rate": 0.5294,
      "recovery_rate": 0.5041,
      "dist_investment": 17000,
      "dist_payout": 8570,
      "ai_hit_count": 0,
      "ai_hit_rate": 0,
      "ai_recovery_rate": 0,
      "lift_vs_ai_only": 0.5041
    },
    {
      "venue_code": 14,
      "venue_name": "鳴門",
      "total_races": 19,
      "hit_count": 13,
      "hit_rate": 0.6842,
      "recovery_rate": 0.4958,
      "dist_investment": 19000,
      "dist_payout": 9420,
      "ai_hit_count": 1,
      "ai_hit_rate": 0.0526,
      "ai_recovery_rate": 0.4579,
      "lift_vs_ai_only": 0.0379
    },
    {
      "venue_code": 18,
      "venue_name": "徳山",
      "total_races": 34,
      "hit_count": 28,
      "hit_rate": 0.8235,
      "recovery_rate": 0.4706,
      "dist_investment": 34000,
      "dist_payout": 16000,
      "ai_hit_count": 6,
      "ai_hit_rate": 0.1765,
      "ai_recovery_rate": 0.7618,
      "lift_vs_ai_only": -0.2912
    },
    {
      "venue_code": 1,
      "venue_name": "桐生",
      "total_races": 19,
      "hit_count": 12,
      "hit_rate": 0.6316,
      "recovery_rate": 0.4337,
      "dist_investment": 19000,
      "dist_payout": 8240,
      "ai_hit_count": 0,
      "ai_hit_rate": 0,
      "ai_recovery_rate": 0,
      "lift_vs_ai_only": 0.4337
    },
    {
      "venue_code": 24,
      "venue_name": "大村",
      "total_races": 7,
      "hit_count": 5,
      "hit_rate": 0.7143,
      "recovery_rate": 0.3357,
      "dist_investment": 7000,
      "dist_payout": 2350,
      "ai_hit_count": 1,
      "ai_hit_rate": 0.1429,
      "ai_recovery_rate": 0.4571,
      "lift_vs_ai_only": -0.1214
    }
  ]
}