{
  "venue_code": 3,
  "venue_name": "江戸川",
  "analysis_date": "2026-01-13",
  "hypotheses": [
    {
      "id": "H001",
      "description": "江戸川は汽水で荒れやすいため、2号艇・3号艇予測が有効",
      "status": "verified",
      "result": "3号艇予測: 111.0%, 2号艇予測: 105.3%"
    },
    {
      "id": "H002",
      "description": "信頼度80%以上のレースは配当が低く、70-79%の方が回収率が高い",
      "status": "verified",
      "result": "2号艇: 信頼度70-79=220.0% vs 80↑=71.9%"
    },
    {
      "id": "H003",
      "description": "1号艇がB級の時、外枠（2-6号艇）予測が有効",
      "status": "tentative",
      "result": "1号艇=B級×2号艇予測: 140.4% - ただし期間検証で再現率33%（2/6期間のみデータあり）"
    },
    {
      "id": "H004",
      "description": "レース番号によって有効な予測が異なる",
      "status": "verified",
      "result": "2号艇→前半(147.7%), 3号艇→中盤後半(122-128%)"
    },
    {
      "id": "H005",
      "description": "3連複は1号艇を含む組み合わせが高回収率",
      "status": "verified",
      "result": "1-2-4: 610.7%(73R), 1-2-3: 494.9%(84R), 1号艇含む: 383.5%(409R)"
    },
    {
      "id": "H006",
      "description": "3連複は後半レース（9-12R）でさらに高回収率",
      "status": "verified",
      "result": "1-2-4_後半: 1107.6%(21R) - 通常の1.8倍"
    },
    {
      "id": "H007",
      "description": "3連単は3連複より有効",
      "status": "rejected",
      "result": "3連単: 19.8%回収率 vs 3連複: 397.5%回収率 - 順番一致の難易度が配当に見合わない"
    },
    {
      "id": "H008",
      "description": "3連複的中時は3連単も的中しやすい",
      "status": "rejected",
      "result": "3連複的中時の3連単的中率: 32.9% - 組み合わせが当たっても順番は約1/3しか当たらない"
    },
    {
      "id": "H009",
      "description": "1着的中時は3連単も当てやすい",
      "status": "rejected",
      "result": "1着的中時の2-3着順番的中率: 12.7% - 1着が当たっても2-3着の順番はほぼ当たらない"
    },
    {
      "id": "H010",
      "description": "1-3-2×高信頼度×後半レースは3連単で有効",
      "status": "tentative",
      "result": "回収率105.4%(13R) - サンプル少なめ、継続検証が必要"
    },
    {
      "id": "H011",
      "description": "1-2-4の3連複は期間によらず安定して高回収",
      "status": "verified",
      "result": "6期間全てで100%超え（174%〜1174%）、再現率100%"
    },
    {
      "id": "H012",
      "description": "1号艇含む3連複は期間によらず安定して高回収",
      "status": "verified",
      "result": "6期間全てで100%超え（183%〜720%）、再現率100%"
    },
    {
      "id": "H013",
      "description": "複勝は低リスクで安定した回収が可能",
      "status": "verified",
      "result": "1号艇×後半: 113.9%（再現率83%）、1号艇予測: 110.5%（再現率67%）"
    },
    {
      "id": "H014",
      "description": "期間検証で再現率60%以上のルールは信頼できる",
      "status": "verified",
      "result": "7ルールが再現率60%以上を達成、特に3連複2ルールは再現率100%"
    },
    {
      "id": "H015",
      "description": "レース厳選で回収率を大幅に向上できる",
      "status": "verified",
      "result": "1-2-4: 610.7% → 後半×信頼度80↑で1224.2%（+613.5%）"
    },
    {
      "id": "H016",
      "description": "後半レースが常に有利",
      "status": "partially_rejected",
      "result": "組み合わせによる: 1-2-4は後半有利(1224%)、1号艇含む(汎用)は中盤有利(548%)"
    }
  ]
}
